lkmltools/__init__.py
lkmltools/abstract_rule.py
lkmltools/bq_writer.py
lkmltools/google_auth_helper.py
lkmltools/lookml.py
lkmltools/lookml_field.py
lkmltools/simple_bq_writer.py
lkmltools/util.py
lkmltools/grapher/__init__.py
lkmltools/grapher/graph_animator.py
lkmltools/grapher/lookml_grapher.py
lkmltools/linter/__init__.py
lkmltools/linter/field_rule.py
lkmltools/linter/lookml_linter.py
lkmltools/linter/rule.py
lkmltools/linter/rule_factory.py
lkmltools/linter/rules/__init__.py
lkmltools/linter/rules/fieldrules/__init__.py
lkmltools/linter/rules/fieldrules/all_caps_rule.py
lkmltools/linter/rules/fieldrules/count_name_rule.py
lkmltools/linter/rules/fieldrules/description_rule.py
lkmltools/linter/rules/fieldrules/drill_down_rule.py
lkmltools/linter/rules/fieldrules/lexicon_rule.py
lkmltools/linter/rules/fieldrules/yesno_name_rule.py
lkmltools/linter/rules/filerules/__init__.py
lkmltools/linter/rules/filerules/data_source_rule.py
lkmltools/linter/rules/filerules/filename_viewname_match_rule.py
lkmltools/linter/rules/filerules/one_view_per_file_rule.py
lkmltools/linter/rules/otherrules/__init__.py
lkmltools/linter/rules/otherrules/no_orphans_rule.py
lkmltools/updater/__init__.py
lkmltools/updater/abstract_sql_reader.py
lkmltools/updater/bq_definitions_provider.py
lkmltools/updater/csv_definitions_provider.py
lkmltools/updater/definition_provider.py
lkmltools/updater/definitions_provider_factory.py
lkmltools/updater/file_modifier.py
lkmltools/updater/lookml_modifier.py
lkmltools/updater/mysql_reader.py
lkmltools/updater/postgres_reader.py
lkmltools/updater/sqlite_reader.py
lookml_tools-2.0.5.dist-info/LICENSE
lookml_tools-2.0.5.dist-info/METADATA
lookml_tools-2.0.5.dist-info/WHEEL
lookml_tools-2.0.5.dist-info/top_level.txt
lookml_tools-2.0.5.dist-info/RECORD
