Metadata-Version: 2.1
Name: lookml-tools
Version: 2.0.5
Summary: Set of tools for handling LookML files: a linter, updater, and grapher
Home-page: https://github.com/ww-tech/lookml-tools
Author: Carl Anderson
Author-email: carl.anderson@weightwatchers.com
License: Apache 2.0
Project-URL: Documentation, https://ww-tech.github.io/lookml-tools/
Project-URL: Source, https://github.com/ww-tech/lookml-tools
Platform: UNKNOWN
Classifier: Programming Language :: Python :: 3.6
Classifier: Programming Language :: Python :: 3.7
Classifier: Operating System :: OS Independent
